LICENSE.txt
MANIFEST.in
README.rst
setup.py
forecastio/__init__.py
forecastio/api.py
forecastio/models.py
forecastio/utils.py
python_forecastio.egg-info/PKG-INFO
python_forecastio.egg-info/SOURCES.txt
python_forecastio.egg-info/dependency_links.txt
python_forecastio.egg-info/requires.txt
python_forecastio.egg-info/top_level.txt