Metadata-Version: 1.0
Name: python-forecastio
Version: 1.3.2
Summary: A thin Python Wrapper for the Forecast.io weather API
Home-page: http://zeevgilovitz.com/python-forecast.io/
Author: Ze'ev Gilovitz
Author-email: zeev.gil@gmail.com
License: BSD 2-clause
Keywords: weather API wrapper forecast.io location
Platform: UNKNOWN
